hana_scaffold/__init__.py
hana_scaffold/breakpoint.py
hana_scaffold/enzyme.py
hana_scaffold/ext_binary.py
hana_scaffold/map.py
hana_scaffold/module.py
hana_scaffold/validator.py
hana_scaffold-1.0.dist-info/METADATA
hana_scaffold-1.0.dist-info/WHEEL
hana_scaffold-1.0.dist-info/top_level.txt
hana_scaffold-1.0.dist-info/RECORD
